irsdk.py
pyirsdk-1.3.4.dist-info/LICENSE
pyirsdk-1.3.4.dist-info/METADATA
pyirsdk-1.3.4.dist-info/WHEEL
pyirsdk-1.3.4.dist-info/entry_points.txt
pyirsdk-1.3.4.dist-info/top_level.txt
pyirsdk-1.3.4.dist-info/RECORD
