Metadata-Version: 2.1
Name: pyirsdk
Version: 1.3.4
Summary: Python 3 implementation of iRacing SDK
Home-page: https://github.com/kutu/pyirsdk
Author: Mihail Latyshov
Author-email: kutu182@gmail.com
License: MIT
Platform: win64
Classifier: Development Status :: 5 - Production/Stable
Classifier: Environment :: Console
Classifier: License :: OSI Approved :: MIT License
Classifier: Operating System :: Microsoft :: Windows
Classifier: Programming Language :: Python :: 3.7
Classifier: Topic :: Utilities
License-File: LICENSE
Requires-Dist: PyYAML (>=5.3)
